soar/__init__.py
soar/config.py
soar/context.py
soar/main.py
soar/datasets/__init__.py
soar/datasets/augment.py
soar/datasets/dataloader.py
soar/datasets/dataset.py
soar/datasets/transform.py
soar/engine/__init__.py
soar/engine/exporter.py
soar/engine/predictor.py
soar/engine/trainer.py
soar/engine/validator.py
soar/models/__init__.py
soar/models/botnet.py
soar/models/model.py
soar/models/resnet.py
soar/utils/__init__.py
soar/utils/crypt.py
soar/utils/ema.py
soar/utils/event.py
soar/utils/logger.py
soar/utils/loss.py
soar/utils/metric.py
soar/utils/optimizer.py
soar/utils/parallel.py
soar/utils/scheduler.py
soar/utils/storager.py
soar/weights/__init__.py
soarv1-0.9.dist-info/METADATA
soarv1-0.9.dist-info/WHEEL
soarv1-0.9.dist-info/top_level.txt
soarv1-0.9.dist-info/RECORD
